algotaf/__init__.py
algotaf/backend/__init__.py
algotaf/backend/config.py
algotaf/backend/apis/__init__.py
algotaf/backend/apis/api_interactor.py
algotaf/backend/db/__init__.py
algotaf/backend/db/db_cacher.py
algotaf/backend/db/db_wrapper.py
algotaf/backend/experiments/__init__.py
algotaf/backend/experiments/keras_testing.py
algotaf/backend/experiments/tensorflowtest.py
algotaf/backend/fileio/__init__.py
algotaf/backend/fileio/apikey.py
algotaf/backend/fileio/db_host.py
algotaf/backend/fileio/sensitive_data.py
algotaf/backend/simulator/HistoricalData.py
algotaf/backend/simulator/Order.py
algotaf/backend/simulator/Portfolio.py
algotaf/backend/simulator/Position.py
algotaf/backend/simulator/TimeSimulator.py
algotaf/backend/simulator/__init__.py
algotaf/backend/simulator/config.py
algotaf/backend/testers/__init__.py
algotaf/backend/testers/back_tester.py
algotaf/backend/testers/front_tester.py
algotaf/frontend/__init__.py
algotaf/old/__init__.py
algotaf/old/test.py
algotaf/other/__init__.py
algotaf/other/benchmark.py
backend/__init__.py
backend/config.py
backend/apis/__init__.py
backend/apis/api_interactor.py
backend/db/__init__.py
backend/db/db_cacher.py
backend/db/db_wrapper.py
backend/experiments/__init__.py
backend/experiments/keras_testing.py
backend/experiments/tensorflowtest.py
backend/fileio/__init__.py
backend/fileio/apikey.py
backend/fileio/db_host.py
backend/fileio/sensitive_data.py
backend/simulator/HistoricalData.py
backend/simulator/Order.py
backend/simulator/Portfolio.py
backend/simulator/Position.py
backend/simulator/TimeSimulator.py
backend/simulator/__init__.py
backend/simulator/config.py
backend/testers/__init__.py
backend/testers/back_tester.py
backend/testers/front_tester.py
frontend/__init__.py
old/__init__.py
old/test.py
other/__init__.py
other/benchmark.py
algotaf-1.2.dist-info/LICENSE
algotaf-1.2.dist-info/METADATA
algotaf-1.2.dist-info/WHEEL
algotaf-1.2.dist-info/top_level.txt
algotaf-1.2.dist-info/RECORD
