Metadata-Version: 2.1
Name: algotaf
Version: 1.2
Summary: UNKNOWN
Home-page: https://github.com/ramasrirama99/AlgoTradeFramework
Author: UNKNOWN
Author-email: UNKNOWN
License: MIT
Platform: UNKNOWN
Requires-Dist: pgcopy
Requires-Dist: psycopg2
Requires-Dist: requests
Requires-Dist: schedule
